README.rst
setup.py
flask_erppeek/__init__.py
flask_erppeek/openerp.py
flask_erppeek.egg-info/PKG-INFO
flask_erppeek.egg-info/SOURCES.txt
flask_erppeek.egg-info/dependency_links.txt
flask_erppeek.egg-info/not-zip-safe
flask_erppeek.egg-info/requires.txt
flask_erppeek.egg-info/top_level.txt