Metadata-Version: 1.1
Name: flask-erppeek
Version: 1.0.0
Summary: ERPPeek Connector for Flask
Home-page: https://github.com/gisce/flask-erppeek
Author: GISCE-TI, S.L.
Author-email: devel@gisce.net
License: BSD
Platform: any
Classifier: Environment :: Web Environment
Classifier: Intended Audience :: Developers
Classifier: License :: OSI Approved :: BSD License
Classifier: Operating System :: OS Independent
Classifier: Programming Language :: Python
Classifier: Topic :: Internet :: WWW/HTTP :: Dynamic Content
Classifier: Topic :: Software Development :: Libraries :: Python Modules
